Workbook

Sheet 📖 Como Usar
A1: 📖 COMO USAR ESSA PLANILHA EM 5 PASSOS
B3: 01 | C3: 💰 Vá na aba RECEITAS e anote tudo que entra no mês — salário, freela, vendas, benefícios. Sem isso, nada funciona.
B5: 02 | C5: 🧾 Em DESPESAS FIXAS, liste o que você paga TODO mês: aluguel, internet, plano de saúde, etc.
B7: 03 | C7: 🛒 Em DESPESAS VARIÁVEIS, anote os gastos do dia a dia: mercado, restaurante, uber, lazer.
B9: 04 | C9: 💳 Tem cartão de crédito? Use a aba CARTÃO. Anote cada compra e parcela — o cartão é o vilão.
B11: 05 | C11: 🎯 Defina suas METAS, calcule sua RESERVA DE EMERGÊNCIA e acompanhe seus INVESTIMENTOS.
B13: ⭐ | C13: Volte ao DASHBOARD pra ver seu progresso, % poupado e onde está vazando dinheiro.
B16: 💪 "Quem não controla o pouco, não controla o muito." Comece HOJE.

Sheet 🏠 Dashboard
A1: MINHA VIDA FINANCEIRA — DASHBOARD MENSAL
B3: Mês de referência: | D3: Janeiro/2026
B5: 💵 RECEITA TOTAL | D5: 💸 DESPESA TOTAL | F5: 📊 SALDO DO MÊS | H5: 🎯 % POUPADO
B6: =SUM('💰 Receitas'!D:D) -> 9530 | D6: =SUM('🧾 Despesas Fixas'!D:D)+SUM('🛒 Despesas Variáveis'!D:D)+SUM('💳 Cartão Crédito'!E:E) -> 10407.48 | F6: =B6-D6 -> -877.48 | H6: =IFERROR(F6/B6,0) -> -0.092075551
A8: RESUMO POR CATEGORIA
B10: Categoria | C10: Gasto | D10: % Receita | F10: META FINANCEIRA | G10: Atual | H10: Meta
B11: Moradia | C11: =SUMIF('🧾 Despesas Fixas'!C:C,B11,'🧾 Despesas Fixas'!D:D) -> 2064 | D11: =IFERROR(C11/$B$6,0) -> 0.21657922 | F11: Reserva Emergência | G11: ='🏦 Reserva Emergência'!C8 -> 1500 | H11: ='🏦 Reserva Emergência'!C5 -> 6
B12: Alimentação | C12: =SUMIF('🛒 Despesas Variáveis'!C:C,B12,'🛒 Despesas Variáveis'!D:D) -> 910 | D12: =IFERROR(C12/$B$6,0) -> 0.095487933 | F12: Viagem dos Sonhos | G12: ='🎯 Metas'!C5 -> 2500 | H12: ='🎯 Metas'!D5 -> 18000
B13: Transporte | C13: =SUMIF('🛒 Despesas Variáveis'!C:C,B13,'🛒 Despesas Variáveis'!D:D)+SUMIF('🧾 Despesas Fixas'!C:C,B13,'🧾 Despesas Fixas'!D:D) -> 335 | D13: =IFERROR(C13/$B$6,0) -> 0.035152151 | F13: Quitar Dívidas | G13: ='🎯 Metas'!C6 -> 800 | H13: ='🎯 Metas'!D6 -> 4500
B14: Lazer | C14: =SUMIF('🛒 Despesas Variáveis'!C:C,B14,'🛒 Despesas Variáveis'!D:D) -> 60 | D14: =IFERROR(C14/$B$6,0) -> 0.0062959077 | F14: Investir Mês | G14: ='💎 Investimentos'!C13 -> 5100 | H14: =B6*0.2 -> 1906
B15: Saúde | C15: =SUMIF('🛒 Despesas Variáveis'!C:C,B15,'🛒 Despesas Variáveis'!D:D)+SUMIF('🧾 Despesas Fixas'!C:C,B15,'🧾 Despesas Fixas'!D:D) -> 605 | D15: =IFERROR(C15/$B$6,0) -> 0.063483736
B16: Educação | C16: =SUMIF('🛒 Despesas Variáveis'!C:C,B16,'🛒 Despesas Variáveis'!D:D)+SUMIF('🧾 Despesas Fixas'!C:C,B16,'🧾 Despesas Fixas'!D:D) -> 147 | D16: =IFERROR(C16/$B$6,0) -> 0.015424974
B17: Outros | C17: =SUMIF('🛒 Despesas Variáveis'!C:C,B17,'🛒 Despesas Variáveis'!D:D) -> 220 | D17: =IFERROR(C17/$B$6,0) -> 0.023084995
B20: 💡 DICA: Tente a regra 50/30/20 — 50% essencial, 30% lazer, 20% investimento. Você está no caminho!

Sheet 💰 Receitas
A1: 💰 RECEITAS DO MÊS
A2: Anote tudo que entra: salário, freelas, vendas, etc. Não esqueça nada.
A4: Data | B4: Descrição | C4: Categoria | D4: Valor | E4: Recebido?
A5: 05/01/2026 | B5: Salário CLT | C5: Salário | D5: 3500 | E5: Sim
A6: 10/01/2026 | B6: Freela design | C6: Extra | D6: 450 | E6: Sim
A7: 15/01/2026 | B7: Venda Mercado Livre | C7: Vendas | D7: 180 | E7: Sim
A8: 25/01/2026 | B8: Vale Refeição | C8: Benefício | D8: 600 | E8: Sim
A9: 30/01/2026 | B9: Cashback cartão | C9: Outros | D9: 35 | E9: Sim
A30: TOTAL | D30: =SUM(D5:D29) -> 4765 | E30: =COUNTIF(E5:E29,"Sim")&" / "&COUNTA(B5:B29) -> 5 / 5

Sheet 🧾 Despesas Fixas
A1: 🧾 DESPESAS FIXAS
A2: Aluguel, internet, plano de saúde... contas que vêm todo mês.
A4: Vencimento | B4: Descrição | C4: Categoria | D4: Valor | E4: Pago?
A5: 05/01/2026 | B5: Aluguel | C5: Moradia | D5: 1200 | E5: Sim
A6: 10/01/2026 | B6: Condomínio | C6: Moradia | D6: 380 | E6: Sim
A7: 12/01/2026 | B7: Internet 500MB | C7: Moradia | D7: 110 | E7: Sim
A8: 15/01/2026 | B8: Energia elétrica | C8: Moradia | D8: 220 | E8: Sim
A9: 18/01/2026 | B9: Água | C9: Moradia | D9: 85 | E9: Sim
A10: 20/01/2026 | B10: Plano celular | C10: Moradia | D10: 69 | E10: Sim
A11: 05/01/2026 | B11: Plano de saúde | C11: Saúde | D11: 390 | E11: Sim
A12: 10/01/2026 | B12: Academia | C12: Saúde | D12: 120 | E12: Sim
A13: 01/01/2026 | B13: Streaming (Netflix+Spotify) | C13: Lazer | D13: 60 | E13: Sim
A14: 05/01/2026 | B14: Transporte (cartão) | C14: Transporte | D14: 250 | E14: Sim
A30: TOTAL FIXAS | D30: =SUM(D5:D29) -> 2884 | E30: =COUNTIF(E5:E29,"Sim")&" / "&COUNTA(B5:B29) -> 10 / 10

Sheet 🛒 Despesas Variáveis
A1: 🛒 DESPESAS VARIÁVEIS
A2: Mercado, restaurante, uber, lazer — gastos que mudam todo mês.
A4: Data | B4: Descrição | C4: Categoria | D4: Valor | E4: Forma Pgto
A5: 03/01/2026 | B5: Mercado mensal | C5: Alimentação | D5: 680 | E5: Débito
A6: 06/01/2026 | B6: Padaria | C6: Alimentação | D6: 45 | E6: Pix
A7: 08/01/2026 | B7: Restaurante c/ namorada | C7: Alimentação | D7: 130 | E7: Crédito
A8: 10/01/2026 | B8: Uber trabalho | C8: Transporte | D8: 85 | E8: Pix
A9: 12/01/2026 | B9: Cinema | C9: Lazer | D9: 60 | E9: Crédito
A10: 15/01/2026 | B10: Farmácia | C10: Saúde | D10: 95 | E10: Pix
A11: 18/01/2026 | B11: Curso online | C11: Educação | D11: 147 | E11: Crédito
A12: 22/01/2026 | B12: iFood | C12: Alimentação | D12: 55 | E12: Pix
A13: 25/01/2026 | B13: Cabeleireiro | C13: Outros | D13: 70 | E13: Pix
A14: 28/01/2026 | B14: Presente de aniversário | C14: Outros | D14: 150 | E14: Crédito
A35: TOTAL VARIÁVEIS | D35: =SUM(D5:D34) -> 1517

Sheet 💳 Cartão Crédito
A1: 💳 CONTROLE DE CARTÃO
A2: Cuidado: o cartão é o vilão silencioso. Anote TUDO.
A4: Data Compra | B4: Descrição | C4: Categoria | D4: Parcelas | E4: Valor Parcela | F4: Valor Total
A5: 02/01/2026 | B5: Tênis novo | C5: Vestuário | D5: 3 | E5: 99.66 | F5: =D5*E5 -> 298.98
A6: 05/01/2026 | B6: Mercado | C6: Alimentação | D6: 1 | E6: 420 | F6: =D6*E6 -> 420
A7: 12/01/2026 | B7: Streaming anual | C7: Lazer | D7: 12 | E7: 23.25 | F7: =D7*E7 -> 279
A8: 18/01/2026 | B8: Curso premium | C8: Educação | D8: 6 | E8: 79.83 | F8: =D8*E8 -> 478.98
A9: 22/01/2026 | B9: Restaurante | C9: Alimentação | D9: 1 | E9: 180 | F9: =D9*E9 -> 180
F10: =IFERROR(D10*E10,"") -> 0
F11: =IFERROR(D11*E11,"") -> 0
F12: =IFERROR(D12*E12,"") -> 0
F13: =IFERROR(D13*E13,"") -> 0
F14: =IFERROR(D14*E14,"") -> 0
F15: =IFERROR(D15*E15,"") -> 0
F16: =IFERROR(D16*E16,"") -> 0
F17: =IFERROR(D17*E17,"") -> 0
F18: =IFERROR(D18*E18,"") -> 0
F19: =IFERROR(D19*E19,"") -> 0
F20: =IFERROR(D20*E20,"") -> 0
F21: =IFERROR(D21*E21,"") -> 0
... F24: =IFERROR(D24*E24,"") -> 0
A25: FATURA TOTAL | E25: =SUM(E5:E24) -> 802.74 | F25: =SUM(F5:F24) -> 1656.96
A27: ⚠️ ALERTA: Soma das parcelas vai pro Dashboard. Cuidado com parcelados — eles travam seu caixa por meses.

Sheet 🎯 Metas
A1: 🎯 METAS FINANCEIRAS
A2: Meta sem prazo é desejo. Coloque DATA e VALOR.
A4: Meta | B4: Prazo | C4: Valor Atual | D4: Valor Alvo | E4: Progresso | F4: Falta Guardar/Mês
A5: Viagem dos Sonhos (Europa) | B5: Dez/2026 | C5: 2500 | D5: 18000 | E5: =IFERROR(C5/D5,0) -> 0.13888889 | F5: =IFERROR((D5-C5)/12,0) -> 1291.6667
A6: Quitar dívida do cartão | B6: Jun/2026 | C6: 800 | D6: 4500 | E6: =IFERROR(C6/D6,0) -> 0.17777778 | F6: =IFERROR((D6-C6)/6,0) -> 616.66667
A7: Trocar de notebook | B7: Out/2026 | C7: 500 | D7: 6000 | E7: =IFERROR(C7/D7,0) -> 0.083333333 | F7: =IFERROR((D7-C7)/10,0) -> 550
A8: Curso de pós-graduação | B8: Mar/2027 | C8: 0 | D8: 12000 | E8: =IFERROR(C8/D8,0) -> 0 | F8: =IFERROR((D8-C8)/14,0) -> 857.14286
A9: Carro novo (entrada) | B9: Dez/2027 | C9: 1200 | D9: 25000 | E9: =IFERROR(C9/D9,0) -> 0.048 | F9: =IFERROR((D9-C9)/24,0) -> 991.66667

Sheet 🏦 Reserva Emergência
A1: 🏦 CALCULADORA — RESERVA DE EMERGÊNCIA
A2: O primeiro passo de QUEM se organiza: 6 meses de despesa guardados.
B4: Sua despesa MENSAL média | C4: =SUM('🧾 Despesas Fixas'!D:D)+SUM('🛒 Despesas Variáveis'!D:D) -> 8802
B5: Quantos meses quer guardar | C5: 6
B6: VALOR DA RESERVA IDEAL | C6: =C4*C5 -> 52812
B8: Quanto você JÁ tem guardado | C8: 1500
B9: Quanto FALTA guardar | C9: =MAX(0,C6-C8) -> 51312
B10: Em quantos meses quer juntar | C10: 12
B11: GUARDE POR MÊS | C11: =C9/C10 -> 4276
B13: 📌 Como funciona: • Reserva de emergência = 6x sua despesa mensal • Guarde em renda fixa com liquidez diária (CDB liquidez D+0, Tesouro Selic) • Só use em EMERGÊNCIAS reais: desemprego, saúde, imprevistos • Antes de investir em outras coisas, COMPLETE a reserva

Sheet 💎 Investimentos
A1: 💎 MEUS INVESTIMENTOS
A2: Acompanhe onde seu dinheiro está rendendo. Diversifique sempre.
A4: Ativo | B4: Tipo | C4: Valor Investido | D4: Rentab. Mês | E4: Valor Atual | F4: Rendimento
A5: Tesouro Selic 2029 | B5: Renda Fixa | C5: 2000 | D5: 0.009 | E5: =C5*(1+D5) -> 2018 | F5: =E5-C5 -> 18
A6: CDB Banco XP | B6: Renda Fixa | C6: 1500 | D6: 0.011 | E6: =C6*(1+D6) -> 1516.5 | F6: =E6-C6 -> 16.5
A7: Fundo Imobiliário HGLG11 | B7: FII | C7: 800 | D7: 0.008 | E7: =C7*(1+D7) -> 806.4 | F7: =E7-C7 -> 6.4
A8: Ações ITSA4 | B8: Ações | C8: 500 | D8: 0.025 | E8: =C8*(1+D8) -> 512.5 | F8: =E8-C8 -> 12.5
A9: BTC (cripto) | B9: Cripto | C9: 300 | D9: 0.03 | E9: =C9*(1+D9) -> 309 | F9: =E9-C9 -> 9
A13: TOTAL INVESTIDO | C13: =SUM(C5:C12) -> 5100 | E13: =SUM(E5:E12) -> 5162.4 | F13: =SUM(F5:F12) -> 62.4
